operatorlookup/LICENSE
operatorlookup/README.MD
operatorlookup/__init__.py
operatorlookup/requirements.txt
operatorlookup/thirdparty.json
operatorlookup-0.10.dist-info/LICENSE.rst
operatorlookup-0.10.dist-info/METADATA
operatorlookup-0.10.dist-info/WHEEL
operatorlookup-0.10.dist-info/top_level.txt
operatorlookup-0.10.dist-info/RECORD
